{"timestamp": 1744164268.348, "value": 8112599.0, "metric_name": "fake_metric_total", "__name__": "fake_metric_total", "instance": "10.10.1.2:50000", "job": "fake_exporter", "label_0": "value_0_value_0", "label_1": "value_1_value_0", "label_2": "value_2_value_0"}
{"timestamp": 1744164273.348, "value": 16029022.0, "metric_name": "fake_metric_total", "__name__": "fake_metric_total", "instance": "10.10.1.2:50000", "job": "fake_exporter", "label_0": "value_0_value_0", "label_1": "value_1_value_0", "label_2": "value_2_value_0"}
{"timestamp": 1744164278.348, "value": 23866149.0, "metric_name": "fake_metric_total", "__name__": "fake_metric_total", "instance": "10.10.1.2:50000", "job": "fake_exporter", "label_0": "value_0_value_0", "label_1": "value_1_value_0", "label_2": "value_2_value_0"}
{"timestamp": 1744164283.348, "value": 31757738.0, "metric_name": "fake_metric_total", "__name__": "fake_metric_total", "instance": "10.10.1.2:50000", "job": "fake_exporter", "label_0": "value_0_value_0", "label_1": "value_1_value_0", "label_2": "value_2_value_0"}
{"timestamp": 1744164288.348, "value": 39597673.0, "metric_name": "fake_metric_total", "__name__": "fake_metric_total", "instance": "10.10.1.2:50000", "job": "fake_exporter", "label_0": "value_0_value_0", "label_1": "value_1_value_0", "label_2": "value_2_value_0"}
{"timestamp": 1744164293.348, "value": 47164135.0, "metric_name": "fake_metric_total", "__name__": "fake_metric_total", "instance": "10.10.1.2:50000", "job": "fake_exporter", "label_0": "value_0_value_0", "label_1": "value_1_value_0", "label_2": "value_2_value_0"}
{"timestamp": 1744164298.348, "value": 54908613.0, "metric_name": "fake_metric_total", "__name__": "fake_metric_total", "instance": "10.10.1.2:50000", "job": "fake_exporter", "label_0": "value_0_value_0", "label_1": "value_1_value_0", "label_2": "value_2_value_0"}
{"timestamp": 1744164303.348, "value": 63114376.0, "metric_name": "fake_metric_total", "__name__": "fake_metric_total", "instance": "10.10.1.2:50000", "job": "fake_exporter", "label_0": "value_0_value_0", "label_1": "value_1_value_0", "label_2": "value_2_value_0"}
{"timestamp": 1744164308.348, "value": 70839602.0, "metric_name": "fake_metric_total", "__name__": "fake_metric_total", "instance": "10.10.1.2:50000", "job": "fake_exporter", "label_0": "value_0_value_0", "label_1": "value_1_value_0", "label_2": "value_2_value_0"}
